address_formatter/__init__.py
address_formatter/formatter.py
pik_address_formatter-1.1.dist-info/LICENSE
pik_address_formatter-1.1.dist-info/METADATA
pik_address_formatter-1.1.dist-info/WHEEL
pik_address_formatter-1.1.dist-info/top_level.txt
pik_address_formatter-1.1.dist-info/RECORD
