Metadata-Version: 2.1
Name: pik-address-formatter
Version: 1.1
Summary: Address formatter for address components from housing
Home-page: https://github.com/pik-software/pik-address-formatter.git
Author: pik-software
Author-email: no-reply@pik-software.ru
License: UNKNOWN
Keywords: apiqa
Platform: UNKNOWN
Classifier: Development Status :: 5 - Production/Stable
Classifier: Intended Audience :: Developers
Classifier: Topic :: Software Development
Classifier: License :: OSI Approved :: MIT License
Classifier: Programming Language :: Python :: 3.6
Requires-Python: ~=3.6
